mielto/__init__.py
mielto/py.typed
mielto/client/__init__.py
mielto/client/async_mielto.py
mielto/client/base.py
mielto/client/exceptions.py
mielto/client/mielto.py
mielto/internals/__init__.py
mielto/internals/embedder/__init__.py
mielto/internals/embedder/base.py
mielto/internals/embedder/fast_embed.py
mielto/internals/vectors/__init__.py
mielto/internals/vectors/base.py
mielto/internals/vectors/enum.py
mielto/internals/vectors/faiss.py
mielto/resources/__init__.py
mielto/resources/chat.py
mielto/resources/collections.py
mielto/resources/compress.py
mielto/resources/memories.py
mielto/tools/__init__.py
mielto/tools/base.py
mielto/tools/definitions.py
mielto/tools/executors.py
mielto/tools/mielto_tools.py
mielto/tools/provider/__init__.py
mielto/tools/provider/openai.py
mielto/types/__init__.py
mielto/types/chat.py
mielto/types/collection.py
mielto/types/compress.py
mielto/types/memory.py
mielto/types/upload.py
mielto-0.1.7.dist-info/licenses/LICENSE
mielto-0.1.7.dist-info/METADATA
mielto-0.1.7.dist-info/WHEEL
mielto-0.1.7.dist-info/top_level.txt
mielto-0.1.7.dist-info/RECORD
