Metadata-Version: 2.4
Name: mielto
Version: 0.1.7
Summary: Official Python client library for Mielto API
Author-email: Mielto <hi@mielto.com>, Toby Oyetoke <toby@mielto.com>
Project-URL: homepage, https://mielto.com
Project-URL: documentation, https://docs.mielto.com
Project-URL: repository, https://github.com/mieltoinc/mielto
Requires-Python: >=3.8
License-File: LICENSE
Requires-Dist: httpx>=0.24.0
Requires-Dist: pydantic>=2.0.0
Requires-Dist: typing-extensions>=4.0.0
Requires-Dist: tqdm>=4.65.0
Requires-Dist: pathspec>=0.11.0
Provides-Extra: vectors
Requires-Dist: faiss-cpu>=1.7.4; extra == "vectors"
Requires-Dist: numpy>=1.24.0; extra == "vectors"
Requires-Dist: fastembed>=0.2.0; extra == "vectors"
Provides-Extra: dev
Requires-Dist: mypy; extra == "dev"
Requires-Dist: pytest; extra == "dev"
Requires-Dist: pytest-asyncio; extra == "dev"
Requires-Dist: pytest-mock; extra == "dev"
Requires-Dist: pytest-cov; extra == "dev"
Requires-Dist: ruff; extra == "dev"
Requires-Dist: faiss-cpu>=1.7.4; extra == "dev"
Requires-Dist: numpy>=1.24.0; extra == "dev"
Requires-Dist: fastembed>=0.2.0; extra == "dev"
Dynamic: license-file
